jeffry_chacon/__init__.py
jeffry_chacon/__main__.py
jeffry_chacon/print_me_funcs.py
jeffry_chacon-0.1.0.dist-info/licenses/LICENCE.TXT
jeffry_chacon-0.1.0.dist-info/METADATA
jeffry_chacon-0.1.0.dist-info/WHEEL
jeffry_chacon-0.1.0.dist-info/entry_points.txt
jeffry_chacon-0.1.0.dist-info/top_level.txt
jeffry_chacon-0.1.0.dist-info/RECORD
