Metadata-Version: 2.4
Name: jeffry_chacon
Version: 0.1.0
Summary: My first package!
Author-email: Jeffry Chacon <jchaconc13@gmail.com>
Maintainer-email: Jeffry Chacon <jchaconc13@gmail.com>
Project-URL: Homepage, https://github.com/
Project-URL: Documentation, https://github.com/
Keywords: Furuness
Classifier: Programming Language :: Python :: 3.9
Classifier: Programming Language :: Python :: Implementation :: CPython
Classifier: License :: OSI Approved :: BSD License
Classifier: Intended Audience :: Developers
Classifier: Operating System :: POSIX :: Linux
Classifier: Operating System :: Microsoft :: Windows
Classifier: Operating System :: MacOS
Classifier: Operating System :: MacOS :: MacOS X
Requires-Python: >=3.9
License-File: LICENCE.TXT
Dynamic: license-file
